st_static_export/__init__.py
st_static_export-0.2.0.dist-info/METADATA
st_static_export-0.2.0.dist-info/WHEEL
st_static_export-0.2.0.dist-info/top_level.txt
st_static_export-0.2.0.dist-info/RECORD
