Metadata-Version: 2.1
Name: st-static-export
Version: 0.2.0
Summary: Provides static HTML export for dataframes and altair charts for Streamlit apps.
Home-page: https://github.com/sqlinsights/st-static-export
Author: Carlos D. Serrano
Author-email: sqlinsights@gmail.com
Classifier: Operating System :: OS Independent
Classifier: Programming Language :: Python :: 3
Classifier: Programming Language :: Python :: 3 :: Only
Classifier: Programming Language :: Python :: 3.9
Requires-Python: >=3.9
Requires-Dist: pandas >=1.5
Requires-Dist: beautifulsoup4 >=4.12
Requires-Dist: altair >=4.2
Requires-Dist: typing-extensions >=4.8.0
Provides-Extra: dev
Requires-Dist: pre-commit ; extra == 'dev'
Requires-Dist: streamlit ; extra == 'dev'
Requires-Dist: vega-datasets ; extra == 'dev'
